django_haystack_es-0.2.6.dist-info/DESCRIPTION.rst
django_haystack_es-0.2.6.dist-info/METADATA
django_haystack_es-0.2.6.dist-info/RECORD
django_haystack_es-0.2.6.dist-info/WHEEL
django_haystack_es-0.2.6.dist-info/metadata.json
django_haystack_es-0.2.6.dist-info/top_level.txt
haystack_es/__init__.py
haystack_es/apps.py
haystack_es/backends.py
haystack_es/fields.py
haystack_es/indexes.py
haystack_es/models.py
haystack_es/query.py
