Metadata-Version: 2.0
Name: django-haystack-es
Version: 0.2.6
Summary: Extended haystack backend for Elasticsearch
Home-page: https://github.com/tehamalab/django-haystack-es
Author: Tehamalab
Author-email: developers@tehamalab.com
License: BSD
Keywords: django-haystack-es
Platform: UNKNOWN
Classifier: Development Status :: 4 - Beta
Classifier: Framework :: Django
Classifier: Framework :: Django :: 1.8
Classifier: Framework :: Django :: 1.9
Classifier: Framework :: Django :: 1.10
Classifier: Framework :: Django :: 1.11
Classifier: Intended Audience :: Developers
Classifier: License :: OSI Approved :: BSD License
Classifier: Natural Language :: English
Classifier: Programming Language :: Python :: 2
Classifier: Programming Language :: Python :: 2.7
Classifier: Programming Language :: Python :: 3
Classifier: Programming Language :: Python :: 3.3
Classifier: Programming Language :: Python :: 3.4
Classifier: Programming Language :: Python :: 3.5
Requires-Dist: django-haystack
Requires-Dist: elasticsearch (>=5.0.0)
